{
	"info": {
		"_postman_id": "6522ea91-9190-40ef-9d53-0d4ee15b4889",
		"name": "Peek Challenge",
		"schema": "https://schema.getpostman.com/json/collection/v2.1.0/collection.json",
		"_exporter_id": "35953292"
	},
	"item": [
		{
			"name": "Ask",
			"request": {
				"method": "POST",
				"header": [],
				"body": {
					"mode": "raw",
					"raw": "{\n    \"thread_id\": \"143\",\n    \"question\": \"How many orders John Doe had in may 2025?\"\n}",
					"options": {
						"raw": {
							"language": "json"
						}
					}
				},
				"url": {
					"raw": "localhost:8080/ask",
					"host": [
						"localhost"
					],
					"port": "8080",
					"path": [
						"ask"
					]
				}
			},
			"response": []
		}
	]
}