[
  {
    "id": 1,
    "name": "John Doe",
    "country": "USA",
    "joinedAt": "2024-01-15T10:30:00Z"
  },
  {
    "id": 2,
    "name": "Jane Smith",
    "country": "USA",
    "joinedAt": "2024-02-20T14:45:00Z"
  },
  {
    "id": 3,
    "name": "Carlos Rodriguez",
    "country": "Brazil",
    "joinedAt": "2024-03-05T09:15:00Z"
  },
  {
    "id": 4,
    "name": "Maria Silva",
    "country": "Brazil",
    "joinedAt": "2024-04-10T16:20:00Z"
  },
  {
    "id": 5,
    "name": "Ronaldinho Gaucho",
    "country": "Brazil",
    "joinedAt": "2024-05-11T16:20:00Z"
  },
  {
    "id": 6,
    "name": "Pierre Dupont",
    "country": "France",
    "joinedAt": "2024-05-12T11:00:00Z"
  },
  {
    "id": 7,
    "name": "Sophie Martin",
    "country": "France",
    "joinedAt": "2024-06-18T13:40:00Z"
  },
  {
    "id": 8,
    "name": "Hiroshi Tanaka",
    "country": "Japan",
    "joinedAt": "2024-07-22T08:50:00Z"
  }
]